README.txt
setup.py
src/nfd2nfc/__init__.py
src/nfd2nfc.egg-info/PKG-INFO
src/nfd2nfc.egg-info/SOURCES.txt
src/nfd2nfc.egg-info/dependency_links.txt
src/nfd2nfc.egg-info/entry_points.txt
src/nfd2nfc.egg-info/not-zip-safe
src/nfd2nfc.egg-info/requires.txt
src/nfd2nfc.egg-info/top_level.txt