Metadata-Version: 1.0
Name: nfd2nfc
Version: 0.1.0
Summary: Convert Mac OSX NFD unicode filename to NFC unicode
Home-page: UNKNOWN
Author: Stephane Klein
Author-email: contact@stephane-klein.info
License: UNKNOWN
Keywords: MacOSX unicode NFD NFC
Platform: UNKNOWN
